isaacus/__init__.py
isaacus/_base_client.py
isaacus/_client.py
isaacus/_compat.py
isaacus/_constants.py
isaacus/_exceptions.py
isaacus/_files.py
isaacus/_models.py
isaacus/_qs.py
isaacus/_resource.py
isaacus/_response.py
isaacus/_streaming.py
isaacus/_types.py
isaacus/_version.py
isaacus/py.typed
isaacus/_utils/__init__.py
isaacus/_utils/_compat.py
isaacus/_utils/_datetime_parse.py
isaacus/_utils/_logs.py
isaacus/_utils/_proxy.py
isaacus/_utils/_reflection.py
isaacus/_utils/_resources_proxy.py
isaacus/_utils/_streams.py
isaacus/_utils/_sync.py
isaacus/_utils/_transform.py
isaacus/_utils/_typing.py
isaacus/_utils/_utils.py
isaacus/lib/.keep
isaacus/resources/__init__.py
isaacus/resources/embeddings.py
isaacus/resources/rerankings.py
isaacus/resources/classifications/__init__.py
isaacus/resources/classifications/classifications.py
isaacus/resources/classifications/universal.py
isaacus/resources/extractions/__init__.py
isaacus/resources/extractions/extractions.py
isaacus/resources/extractions/qa.py
isaacus/types/__init__.py
isaacus/types/embedding_create_params.py
isaacus/types/embedding_response.py
isaacus/types/reranking_create_params.py
isaacus/types/reranking_response.py
isaacus/types/classifications/__init__.py
isaacus/types/classifications/universal_classification_response.py
isaacus/types/classifications/universal_create_params.py
isaacus/types/extractions/__init__.py
isaacus/types/extractions/answer_extraction_response.py
isaacus/types/extractions/qa_create_params.py
isaacus-0.9.1.dist-info/METADATA
isaacus-0.9.1.dist-info/WHEEL
isaacus-0.9.1.dist-info/licenses/LICENSE
isaacus-0.9.1.dist-info/RECORD
